PyTerrGen/.gitignore
PyTerrGen/__init__.py
PyTerrGen/cells.py
PyTerrGen/grid.py
PyTerrGen/main.py
PyTerrGen/style.qss
PyTerrGen/ui/__init__.py
PyTerrGen/ui/grid_ui.py
PyTerrGen/ui/main.py
PyTerrGen/ui/main_window.py
PyTerrGen/ui/widgets.py
PyTerrGen/ui/assets/.readme/automata.png
PyTerrGen/ui/assets/.readme/generation.gif
PyTerrGen/ui/assets/.readme/generation_stage12.png
PyTerrGen/ui/assets/.readme/logo.png
PyTerrGen/ui/assets/.readme/sidepanel.png
PyTerrGen/ui/assets/.readme/ui.png
PyTerrGen/ui/assets/desert/cacti.png
PyTerrGen/ui/assets/desert/pyramid1.png
PyTerrGen/ui/assets/desert/pyramid2.png
PyTerrGen/ui/assets/desert/pyramid3.png
PyTerrGen/ui/assets/desert/pyramid4.png
PyTerrGen/ui/assets/desert/wasteland.png
PyTerrGen/ui/assets/forest/birch.png
PyTerrGen/ui/assets/forest/oak.png
PyTerrGen/ui/assets/forest/pine.png
PyTerrGen/ui/assets/mountain/peaky.png
PyTerrGen/ui/assets/mountain/steep.png
PyTerrGen/ui/assets/plains/grassy.png
PyTerrGen/ui/assets/plains/house1.png
PyTerrGen/ui/assets/plains/house2.png
PyTerrGen/ui/assets/plains/house3.png
PyTerrGen/ui/assets/plains/house4.png
PyTerrGen/ui/assets/snowy/mountain.png
PyTerrGen/ui/assets/snowy/snowy.png
PyTerrGen/ui/assets/swamp/swamp.png
PyTerrGen/ui/assets/water/ship1.png
PyTerrGen/ui/assets/water/ship2.png
PyTerrGen/ui/assets/water/ship3.png
PyTerrGen/ui/assets/water/ship4.png
PyTerrGen/ui/assets/water/wavy1.png
PyTerrGen/ui/assets/water/wavy2.png
PyTerrGen/ui/assets/water/wavy3.png
PyTerrGen/ui/assets/water/wavy4.png
pyterrgen-0.0.1.40.dist-info/METADATA
pyterrgen-0.0.1.40.dist-info/WHEEL
pyterrgen-0.0.1.40.dist-info/entry_points.txt
pyterrgen-0.0.1.40.dist-info/licenses/LICENSE
pyterrgen-0.0.1.40.dist-info/RECORD
