Metadata-Version: 2.3
Name: PyTerrGen
Version: 0.0.1.40
Summary: Procedural map generation with cellular automata in Python
Project-URL: Homepage, https://github.com/n1n1n1q/Terrain-Generation
Project-URL: Issues, https://github.com/n1n1n1q/Terrain-Generation/issues
Author: Oleh, Anna, Viktor
License-File: LICENSE
Classifier: License :: OSI Approved :: MIT License
Classifier: Operating System :: OS Independent
Classifier: Programming Language :: Python :: 3
Requires-Python: >=3.11
Requires-Dist: contourpy==1.2.1
Requires-Dist: cycler==0.12.1
Requires-Dist: fonttools==4.51.0
Requires-Dist: kiwisolver==1.4.5
Requires-Dist: matplotlib==3.8.4
Requires-Dist: numpy==1.26.4
Requires-Dist: packaging==24.0
Requires-Dist: pillow==10.3.0
Requires-Dist: pyparsing==3.1.2
Requires-Dist: pyside6-addons==6.7.0
Requires-Dist: pyside6-essentials==6.7.0
Requires-Dist: pyside6==6.7.0
Requires-Dist: python-dateutil==2.9.0.post0
Requires-Dist: setuptools==69.5.1
Requires-Dist: shiboken6==6.7.0
Requires-Dist: six==1.16.0
